match_recognize/__init__.py
pandas_match_recognize/__init__.py
pandas_match_recognize-0.1.7.dist-info/licenses/LICENSE
src/TestAggregationsInRowPatternMatching.java
src/TestRowPatternMatching.java
src/__init__.py
src/ast_nodes/__init__.py
src/ast_nodes/ast_nodes.py
src/config/__init__.py
src/config/production_config.py
src/executor/__init__.py
src/executor/match_recognize.py
src/grammar/TrinoLexer.g4
src/grammar/TrinoLexer.interp
src/grammar/TrinoLexer.py
src/grammar/TrinoLexer.tokens
src/grammar/TrinoParser.g4
src/grammar/TrinoParser.interp
src/grammar/TrinoParser.py
src/grammar/TrinoParser.tokens
src/grammar/TrinoParserListener.py
src/grammar/TrinoParserVisitor.py
src/grammar/__init__.py
src/matcher/__init__.py
src/matcher/automata.py
src/matcher/condition_evaluator.py
src/matcher/dfa.py
src/matcher/evaluation_utils.py
src/matcher/matcher.py
src/matcher/measure_evaluator.py
src/matcher/pattern_tokenizer.py
src/matcher/production_aggregates.py
src/matcher/row_context.py
src/monitoring/__init__.py
src/monitoring/cache_monitor.py
src/monitoring/health_check.py
src/monitoring/production_logging.py
src/parser/__init__.py
src/parser/error_listeners.py
src/parser/match_recognize_extractor.py
src/parser/query_parser.py
src/pattern/__init__.py
src/pattern/permute_handler.py
src/utils/__init__.py
src/utils/logging_config.py
src/utils/memory_management.py
src/utils/pattern_cache.py
src/utils/performance_optimizer.py
src/utils/production_logging.py
pandas_match_recognize-0.1.7.dist-info/METADATA
pandas_match_recognize-0.1.7.dist-info/WHEEL
pandas_match_recognize-0.1.7.dist-info/top_level.txt
pandas_match_recognize-0.1.7.dist-info/RECORD
