Metadata-Version: 2.4
Name: pandas-match-recognize
Version: 0.1.7
Summary: SQL MATCH_RECOGNIZE for Pandas DataFrames
Home-page: https://github.com/MonierAshraf/Row_match_recognize
Author: MonierAshraf
Author-email: MonierAshraf <your.email@example.com>
License: MIT
Project-URL: Homepage, https://github.com/MonierAshraf/Row_match_recognize
Project-URL: Repository, https://github.com/MonierAshraf/Row_match_recognize
Project-URL: Bug Reports, https://github.com/MonierAshraf/Row_match_recognize/issues
Project-URL: Documentation, https://github.com/MonierAshraf/Row_match_recognize/blob/master/README.md
Keywords: sql,match_recognize,pandas,pattern matching,data science,analytics
Classifier: Development Status :: 4 - Beta
Classifier: Intended Audience :: Developers
Classifier: Intended Audience :: Science/Research
Classifier: License :: OSI Approved :: MIT License
Classifier: Programming Language :: Python :: 3
Classifier: Programming Language :: Python :: 3.7
Classifier: Programming Language :: Python :: 3.8
Classifier: Programming Language :: Python :: 3.9
Classifier: Programming Language :: Python :: 3.10
Classifier: Programming Language :: Python :: 3.11
Classifier: Programming Language :: Python :: 3.12
Classifier: Topic :: Scientific/Engineering
Classifier: Topic :: Database
Classifier: Topic :: Software Development :: Libraries :: Python Modules
Requires-Python: >=3.7
License-File: LICENSE
Requires-Dist: pandas>=1.0.0
Requires-Dist: numpy>=1.18.0
Requires-Dist: antlr4-python3-runtime>=4.9.0
Provides-Extra: dev
Requires-Dist: pytest>=6.0; extra == "dev"
Requires-Dist: pytest-cov; extra == "dev"
Requires-Dist: black; extra == "dev"
Requires-Dist: flake8; extra == "dev"
Requires-Dist: jupyter; extra == "dev"
Requires-Dist: matplotlib; extra == "dev"
Requires-Dist: seaborn; extra == "dev"
Provides-Extra: performance
Requires-Dist: polars>=0.15.0; extra == "performance"
Requires-Dist: psutil>=5.8.0; extra == "performance"
Dynamic: author
Dynamic: home-page
Dynamic: license-file
Dynamic: requires-python
